psswd_box/__init__.py
psswd_box/app.py
psswd_box/password_generator.py
psswd_box/yaml_file_handler.py
psswd_box/resources/PYPI_README.md
psswd_box/resources/configs/config.yaml
psswd_box/resources/configs/themes.yaml
psswd_box/resources/gifs/app_install_uninstall_showcase.gif
psswd_box/resources/gifs/app_showcase.gif
psswd_box/resources/images/psswd_box-128.png
psswd_box/resources/images/psswd_box-16.png
psswd_box/resources/images/psswd_box-256.png
psswd_box/resources/images/psswd_box-32.png
psswd_box/resources/images/psswd_box-512.png
psswd_box/resources/images/psswd_box-64.png
psswd_box-1.3.3.dist-info/METADATA
psswd_box-1.3.3.dist-info/WHEEL
psswd_box-1.3.3.dist-info/entry_points.txt
psswd_box-1.3.3.dist-info/licenses/LICENSE
psswd_box-1.3.3.dist-info/RECORD
