Metadata-Version: 2.4
Name: psswd_box
Version: 1.3.3
Summary: Password generator that never leaves your machine.
Project-URL: repository, https://codeberg.org/melvinquick/psswd_box
Project-URL: issues, https://codeberg.org/melvinquick/psswd_box/issues
Author-email: Melvin Quick <melvinquick@proton.me>
License-Expression: MIT
License-File: LICENSE
Requires-Python: >=3.12
Requires-Dist: pyside6>=6.8.2.1
Requires-Dist: pyyaml>=6.0.2
Requires-Dist: setuptools>=77.0.3
